LICENSE
README.md
setup.cfg
setup.py
icmplib/__init__.py
icmplib/exceptions.py
icmplib/models.py
icmplib/multiping.py
icmplib/ping.py
icmplib/sockets.py
icmplib/traceroute.py
icmplib/utils.py
icmplibs.egg-info/PKG-INFO
icmplibs.egg-info/SOURCES.txt
icmplibs.egg-info/dependency_links.txt
icmplibs.egg-info/top_level.txt