Metadata-Version: 2.1
Name: icmplibs
Version: 3.0.4
Summary: Easily forge ICMP packets and make your own ping and traceroute.
Home-page: https://github.com/ValentinBELYN/icmplib
Author: Valentin BELYN
Author-email: valentin-hello@gmx.com
License: GNU Lesser General Public License v3.0
Keywords: icmp,sockets,ping,multiping,traceroute,async,asyncio,ipv4,ipv6,python,python3
Platform: UNKNOWN
Classifier: Development Status :: 5 - Production/Stable
Classifier: Intended Audience :: Developers
Classifier: License :: OSI Approved :: GNU Lesser General Public License v3 (LGPLv3)
Classifier: Operating System :: OS Independent
Classifier: Programming Language :: Python
Classifier: Programming Language :: Python :: 3
Classifier: Programming Language :: Python :: 3 :: Only
Classifier: Programming Language :: Python :: 3.7
Classifier: Programming Language :: Python :: 3.8
Classifier: Programming Language :: Python :: 3.9
Classifier: Programming Language :: Python :: 3.10
Classifier: Programming Language :: Python :: 3.11
Classifier: Programming Language :: Python :: 3.12
Classifier: Topic :: Software Development :: Libraries
Classifier: Topic :: Software Development :: Libraries :: Python Modules
Requires-Python: >=3.7
License-File: LICENSE
